MANIFEST.in
README.md
requirements-dev.txt
requirements.txt
setup.cfg
setup.py
simio_di/__init__.py
simio_di/containers.py
simio_di/injector.py
simio_di/utils.py
simio_di.egg-info/PKG-INFO
simio_di.egg-info/SOURCES.txt
simio_di.egg-info/dependency_links.txt
simio_di.egg-info/requires.txt
simio_di.egg-info/top_level.txt