Metadata-Version: 2.1
Name: simio-di
Version: 0.1.2
Summary: Small and simple Dependency Injector. Made for Simio framework
Home-page: https://github.com/RB387/simio-di
Author: Nikita Zavadin
Author-email: zavadin142@gmail.com
License: Apache 2.0
Platform: UNKNOWN
Classifier: Programming Language :: Python :: 3
Classifier: Operating System :: OS Independent
Classifier: Framework :: AsyncIO
Classifier: License :: OSI Approved :: Apache Software License
Requires-Python: >=3.7
